pyfinmod/__init__.py
pyfinmod/basic.py
pyfinmod/constants.py
pyfinmod/ev.py
pyfinmod/financials.py
pyfinmod/wacc.py
pyfinmod-0.2.2.dist-info/LICENSE
pyfinmod-0.2.2.dist-info/METADATA
pyfinmod-0.2.2.dist-info/WHEEL
pyfinmod-0.2.2.dist-info/top_level.txt
pyfinmod-0.2.2.dist-info/RECORD
