Metadata-Version: 2.1
Name: pyfinmod
Version: 0.2.2
Summary: Financial modelling in Python
Home-page: https://github.com/leonarduschen/pyfinmod
Author: Alexey Smirnov
Author-email: msc.smirnov.am@gmail.com
Maintainer: leonarduschen
Maintainer-email: leonardus.chen@gmail.com
License: MIT
Platform: UNKNOWN
Requires-Dist: pandas (>=0.23.4)
Requires-Dist: python-dateutil (>=2.7.5)
Requires-Dist: scipy (>=1.1.0)
Requires-Dist: requests (>=2.21.0)
Requires-Dist: tables (>=3.4.4)
